apikit/__init__.py
apikit/convenience.py
sqre_apikit-0.1.2.dist-info/DESCRIPTION.rst
sqre_apikit-0.1.2.dist-info/METADATA
sqre_apikit-0.1.2.dist-info/RECORD
sqre_apikit-0.1.2.dist-info/WHEEL
sqre_apikit-0.1.2.dist-info/metadata.json
sqre_apikit-0.1.2.dist-info/top_level.txt
