Metadata-Version: 2.0
Name: sqre-apikit
Version: 0.1.2
Summary: LSST Data Management SQuaRE microservice tools
Home-page: https://github.com/lsst-sqre/sqre-apikit
Author: Adam Thornton
Author-email: athornton@lsst.org
License: MIT
Keywords: lsst
Platform: UNKNOWN
Classifier: Development Status :: 4 - Beta
Classifier: Programming Language :: Python :: 2.7
Classifier: Programming Language :: Python :: 3.5
Classifier: License :: OSI Approved :: MIT License
Requires-Dist: Flask (==0.11.1)
Requires-Dist: future (==0.16.0)
Requires-Dist: requests (<3.0.0,>=2.13.0)
Requires-Dist: structlog (>=16.1.0)
